pypp_opengl/__init__.py
pypp_opengl/custom.py
pypp_opengl/glad_loader.py
pypp_opengl/pypp_data/cpp/pypp_opengl/custom.cpp
pypp_opengl/pypp_data/cpp/pypp_opengl/custom.h
pypp_opengl/pypp_data/transpiler_config/always_pass_by_value.json
pypp_opengl/pypp_data/transpiler_config/attr_map.json
pypp_opengl/pypp_data/transpiler_config/call_map.json
pypp_opengl/pypp_data/transpiler_config/cmake_lists.json
pypp_opengl/pypp_data/transpiler_config/mapping_functions/gl_attr.py
pypp_opengl/pypp_data/transpiler_config/mapping_functions/glad_load_gl.py
pypp_opengl/pypp_data/transpiler_config/mapping_functions/np_array.py
pypp_opengl-1.0.1a0.dist-info/METADATA
pypp_opengl-1.0.1a0.dist-info/WHEEL
pypp_opengl-1.0.1a0.dist-info/licenses/LICENSE
pypp_opengl-1.0.1a0.dist-info/RECORD
