Metadata-Version: 2.4
Name: pypp-opengl
Version: 1.0.1a0
Summary: A Py++ library for OpenGL
Project-URL: Homepage, https://github.com/curtispuetz/pypp-opengl
Author-email: Curtis Puetz <pypp.main@yahoo.com>
License: MIT
License-File: LICENSE
Requires-Python: >=3.13
Requires-Dist: numpy
Requires-Dist: pyopengl
